.clang-format
.gitignore
LICENSE.txt
MANIFEST.in
README.md
pyproject.toml
setup.py
BoltzTraP2/__init__.py
BoltzTraP2/bandlib.py
BoltzTraP2/dft.py
BoltzTraP2/fd.py
BoltzTraP2/fermisurface.py
BoltzTraP2/fermisurface_2d.py
BoltzTraP2/fite.py
BoltzTraP2/interface.py
BoltzTraP2/io.py
BoltzTraP2/misc.py
BoltzTraP2/serialization.py
BoltzTraP2/units.py
BoltzTraP2/version.py
BoltzTraP2.egg-info/PKG-INFO
BoltzTraP2.egg-info/SOURCES.txt
BoltzTraP2.egg-info/dependency_links.txt
BoltzTraP2.egg-info/entry_points.txt
BoltzTraP2.egg-info/requires.txt
BoltzTraP2.egg-info/top_level.txt
BoltzTraP2/sphere/__init__.py
BoltzTraP2/sphere/backend.cpp
BoltzTraP2/sphere/backend.hpp
BoltzTraP2/sphere/backend.pxd
BoltzTraP2/sphere/frontend.cpp
BoltzTraP2/sphere/frontend.pyx
examples/Bi2Te3.py
examples/Bi2Te3_Kappa.py
examples/CoSb3.py
examples/LZS.py
examples/LZS2.py
examples/Li_bcc.py
examples/Si_btp.py
examples/Si_conv.py
examples/Si_mommat.py
examples/Si_pocket.py
examples/TiCoSb.py
examples/environment.py
examples/parabolic.py
external/eigen-eigen-3215c06819b9/.hg_archival.txt
external/eigen-eigen-3215c06819b9/.hgeol
external/eigen-eigen-3215c06819b9/.hgignore
external/eigen-eigen-3215c06819b9/.hgtags
external/eigen-eigen-3215c06819b9/CMakeLists.txt
external/eigen-eigen-3215c06819b9/COPYING.BSD
external/eigen-eigen-3215c06819b9/COPYING.GPL
external/eigen-eigen-3215c06819b9/COPYING.LGPL
external/eigen-eigen-3215c06819b9/COPYING.MINPACK
external/eigen-eigen-3215c06819b9/COPYING.MPL2
external/eigen-eigen-3215c06819b9/COPYING.README
external/eigen-eigen-3215c06819b9/CTestConfig.cmake
external/eigen-eigen-3215c06819b9/CTestCustom.cmake.in
external/eigen-eigen-3215c06819b9/INSTALL
external/eigen-eigen-3215c06819b9/README.md
external/eigen-eigen-3215c06819b9/eigen3.pc.in
external/eigen-eigen-3215c06819b9/signature_of_eigen3_matrix_library
external/eigen-eigen-3215c06819b9/Eigen/CMakeLists.txt
external/eigen-eigen-3215c06819b9/Eigen/Cholesky
external/eigen-eigen-3215c06819b9/Eigen/CholmodSupport
external/eigen-eigen-3215c06819b9/Eigen/Core
external/eigen-eigen-3215c06819b9/Eigen/Dense
external/eigen-eigen-3215c06819b9/Eigen/Eigen
external/eigen-eigen-3215c06819b9/Eigen/Eigenvalues
