Metadata-Version: 2.1
Name: BoltzTraP2
Version: 24.9.4
Summary: band-structure interpolator and transport coefficient calculator
Author-email: "Georg K. H. Madsen" <georg.madsen@tuwien.ac.at>
License: GPLv3+
Project-URL: Homepage, https://www.boltztrap.org
Project-URL: Download, https://gitlab.com/sousaw/BoltzTraP2/repository/archive.tar.gz?ref=v24.9.4
Keywords: electronic band structure,Onsager,thermoelectric coefficients
Classifier: Development Status :: 4 - Beta
Classifier: Intended Audience :: Science/Research
Classifier: Programming Language :: Python :: 3
Classifier: Programming Language :: Python :: 3.9
Classifier: Programming Language :: Python :: 3.10
Classifier: Programming Language :: Python :: 3.11
Classifier: Programming Language :: Python :: 3.12
Classifier: Programming Language :: C++
Classifier: License :: OSI Approved :: GNU General Public License v3 or later (GPLv3+)
Classifier: Topic :: Scientific/Engineering :: Physics
Classifier: Topic :: Scientific/Engineering :: Chemistry
Requires-Python: >=3.9
License-File: LICENSE.txt
Requires-Dist: spglib
Requires-Dist: numpy
Requires-Dist: scipy
Requires-Dist: matplotlib
Requires-Dist: ase
Requires-Dist: netCDF4
Requires-Dist: cython
Provides-Extra: test
Requires-Dist: pytest; extra == "test"
Provides-Extra: optional
Requires-Dist: gpaw; extra == "optional"
Requires-Dist: pyfftw; extra == "optional"
